README.rst
multisuite.py
setup.py
multisuite.egg-info/PKG-INFO
multisuite.egg-info/SOURCES.txt
multisuite.egg-info/dependency_links.txt
multisuite.egg-info/entry_points.txt
multisuite.egg-info/requires.txt
multisuite.egg-info/top_level.txt