Metadata-Version: 1.0
Name: multisuite
Version: 0.2.1
Summary: run independent nose test suites together
Home-page: https://github.com/DFE/multisuite
Author: Project MONK Developers
Author-email: project-monk@dreserach-fe.de
License: LICENSE
Platform: UNKNOWN
